odoo/addons/donation_mass/README.rst
odoo/addons/donation_mass/__init__.py
odoo/addons/donation_mass/__manifest__.py
odoo/addons/donation_mass/data/product.xml
odoo/addons/donation_mass/demo/demo_data.xml
odoo/addons/donation_mass/i18n/donation_mass.pot
odoo/addons/donation_mass/i18n/fr.po
odoo/addons/donation_mass/models/__init__.py
odoo/addons/donation_mass/models/donation.py
odoo/addons/donation_mass/models/mass.py
odoo/addons/donation_mass/models/product.py
odoo/addons/donation_mass/readme/CONFIGURE.rst
odoo/addons/donation_mass/readme/CONTRIBUTORS.rst
odoo/addons/donation_mass/readme/DESCRIPTION.rst
odoo/addons/donation_mass/readme/USAGE.rst
odoo/addons/donation_mass/security/ir.model.access.csv
odoo/addons/donation_mass/static/description/icon.png
odoo/addons/donation_mass/static/description/index.html
odoo/addons/donation_mass/tests/__init__.py
odoo/addons/donation_mass/tests/test_donation_mass.py
odoo/addons/donation_mass/views/donation.xml
odoo/addons/donation_mass/views/mass.xml
odoo14_addon_donation_mass-14.0.1.2.0.dist-info/METADATA
odoo14_addon_donation_mass-14.0.1.2.0.dist-info/WHEEL
odoo14_addon_donation_mass-14.0.1.2.0.dist-info/top_level.txt
odoo14_addon_donation_mass-14.0.1.2.0.dist-info/RECORD
